tblite/__init__.py
tblite/_libtblite.cpython-39-x86_64-linux-gnu.so
tblite/ase.py
tblite/exceptions.py
tblite/interface.py
tblite/library.py
tblite/py.typed
tblite/qcschema.py
tblite/test_ase.py
tblite/test_interface.py
tblite/test_library.py
tblite/test_qcschema.py
tblite-0.5.0.data/data/licenses/mctc-lib/jsonfortran/LICENSE
tblite.libs/libblas-357956a1.so.3.4.2
tblite.libs/libgfortran-91cc3cb1.so.3.0.0
tblite.libs/libgomp-a34b3233.so.1.0.0
tblite.libs/liblapack-1ad85175.so.3.4.2
tblite.libs/libquadmath-96973f99.so.0.0.0
tblite-0.5.0.dist-info/METADATA
tblite-0.5.0.dist-info/WHEEL
tblite-0.5.0.dist-info/RECORD
